code_hacker/__init__.py
code_hacker/api.py
code_hacker/middleware.py
code_hacker/response.py
code_hacker-0.0.3.dist-info/METADATA
code_hacker-0.0.3.dist-info/WHEEL
code_hacker-0.0.3.dist-info/top_level.txt
code_hacker-0.0.3.dist-info/RECORD
