Metadata-Version: 2.1
Name: code-hacker
Version: 0.0.3
Summary: code_hacker web Framework built for learning purposes.
Author: Shahriar Hossain
Author-email: shariarhossain23@gmail.com
License: MIT
Classifier: Development Status :: 3 - Alpha
Classifier: Intended Audience :: Developers
Classifier: License :: OSI Approved :: MIT License
Classifier: Programming Language :: Python :: 3
Classifier: Programming Language :: Python :: 3.6
Classifier: Programming Language :: Python :: 3.7
Classifier: Programming Language :: Python :: 3.8
Classifier: Programming Language :: Python :: 3.9
Classifier: Topic :: Internet :: WWW/HTTP :: WSGI :: Application
Requires-Python: >=3.6.0
Requires-Dist: Jinja2==3.1.2
Requires-Dist: WebOb==1.8.7
Requires-Dist: parse==1.19.0
Requires-Dist: requests-wsgi-adapter==0.4.1
Requires-Dist: requests==2.28.1
Requires-Dist: whitenoise==6.2.0
